neutraltemplate-1.3.2.dist-info/METADATA
neutraltemplate-1.3.2.dist-info/WHEEL
neutraltemplate-1.3.2.dist-info/licenses/LICENSE
neutraltemplate/__init__.py
neutraltemplate/neutraltemplate.cp311-win_amd64.pyd
neutraltemplate-1.3.2.dist-info/RECORD
