Metadata-Version: 2.4
Name: neutraltemplate
Version: 1.3.2
Classifier: Programming Language :: Rust
Classifier: Programming Language :: Python :: Implementation :: CPython
Classifier: Programming Language :: Python :: Implementation :: PyPy
License-File: LICENSE
Summary: Neutralts template engine for the Web, python package
Keywords: template-engine,web,jinja2,flask
License-Expression: Apache License 2.0
Requires-Python: >=3.8
Project-URL: Homepage, https://github.com/FranBarInstance/neutralts
Project-URL: Documentation, https://franbarinstance.github.io/neutralts-docs/docs/neutralts/
Project-URL: Repository, https://github.com/FranBarInstance/neutraltemplate
Project-URL: Rust, https://crates.io/crates/neutralts
Project-URL: Issues, https://github.com/FranBarInstance/neutraltemplate/issues
